summary/__init__.py
summary/_version.py
summary/app.cfg
summary/exceptions.py
summary/summarize.py
summary/version.txt
text_summary-0.1.0.dist-info/METADATA
text_summary-0.1.0.dist-info/RECORD
text_summary-0.1.0.dist-info/WHEEL
text_summary-0.1.0.dist-info/entry_points.txt
text_summary-0.1.0.dist-info/top_level.txt
